publigit/__init__.py
publigit/cli.py
publigit/ensure_github.py
publigit/pypirc.py
publigit-0.2.0.dist-info/METADATA
publigit-0.2.0.dist-info/WHEEL
publigit-0.2.0.dist-info/entry_points.txt
publigit-0.2.0.dist-info/top_level.txt
publigit-0.2.0.dist-info/RECORD
