Metadata-Version: 2.4
Name: publigit
Version: 0.2.0
Requires-Python: >=3.10
Requires-Dist: build
Requires-Dist: twine
Requires-Dist: packaging
Requires-Dist: tomli; python_version < "3.11"
